mongodb_dataset/__init__.py
mongodb_dataset/database.py
mongodb_dataset/expression.py
mongodb_dataset-0.2.0.dist-info/LICENSE
mongodb_dataset-0.2.0.dist-info/WHEEL
mongodb_dataset-0.2.0.dist-info/METADATA
mongodb_dataset-0.2.0.dist-info/RECORD
