Metadata-Version: 2.1
Name: mongodb-dataset
Version: 0.2.0
Summary: Pythonic wrapper around pymongo that can act as a drop-in replacement for dataset
Home-page: https://github.com/TadpoleTutoring/mongodb-dataset
License: MIT
Author: InnovativeInventor
Author-email: root@max.fan
Requires-Python: >=3.8,<4.0
Classifier: Development Status :: 5 - Production/Stable
Classifier: Intended Audience :: Developers
Classifier: License :: OSI Approved :: MIT License
Classifier: Programming Language :: Python :: 3
Classifier: Programming Language :: Python :: 3.8
Classifier: Topic :: Software Development :: Libraries :: Python Modules
Requires-Dist: dnspython (>=1.16.0,<2.0.0)
Requires-Dist: pymongo (>=3.10.1,<4.0.0)
Requires-Dist: pytest-race (>=0.1.1,<0.2.0)
Project-URL: Repository, https://github.com/TadpoleTutoring/mongodb-dataset
